odoo/addons/sale_promotion_discount_in_field_order_line_link/README.rst
odoo/addons/sale_promotion_discount_in_field_order_line_link/__init__.py
odoo/addons/sale_promotion_discount_in_field_order_line_link/__manifest__.py
odoo/addons/sale_promotion_discount_in_field_order_line_link/i18n/it.po
odoo/addons/sale_promotion_discount_in_field_order_line_link/i18n/sale_promotion_discount_in_field_order_line_link.pot
odoo/addons/sale_promotion_discount_in_field_order_line_link/models/__init__.py
odoo/addons/sale_promotion_discount_in_field_order_line_link/models/sale_order.py
odoo/addons/sale_promotion_discount_in_field_order_line_link/readme/CONTRIBUTORS.rst
odoo/addons/sale_promotion_discount_in_field_order_line_link/readme/DESCRIPTION.rst
odoo/addons/sale_promotion_discount_in_field_order_line_link/readme/USAGE.rst
odoo/addons/sale_promotion_discount_in_field_order_line_link/static/description/icon.png
odoo/addons/sale_promotion_discount_in_field_order_line_link/static/description/index.html
odoo/addons/sale_promotion_discount_in_field_order_line_link/tests/__init__.py
odoo/addons/sale_promotion_discount_in_field_order_line_link/tests/test_promotion_discount_in_field.py
odoo14_addon_sale_promotion_discount_in_field_order_line_link-14.0.1.0.1.dev4.dist-info/METADATA
odoo14_addon_sale_promotion_discount_in_field_order_line_link-14.0.1.0.1.dev4.dist-info/WHEEL
odoo14_addon_sale_promotion_discount_in_field_order_line_link-14.0.1.0.1.dev4.dist-info/top_level.txt
odoo14_addon_sale_promotion_discount_in_field_order_line_link-14.0.1.0.1.dev4.dist-info/RECORD
